sknni/__init__.py
sknni-1.0.0.dist-info/LICENSE.txt
sknni-1.0.0.dist-info/METADATA
sknni-1.0.0.dist-info/WHEEL
sknni-1.0.0.dist-info/top_level.txt
sknni-1.0.0.dist-info/RECORD
