Metadata-Version: 2.1
Name: sknni
Version: 1.0.0
Summary: Spherical k-nearest neighbors interpolation
Home-page: https://github.com/PhTrempe/sknni
Author: Philippe Trempe
Author-email: pht@ieee.org
License: MIT
Project-URL: Source, https://github.com/PhTrempe/sknni
Project-URL: Issues, https://github.com/PhTrempe/sknni/issues
Keywords: spherical k-nearest-neighbors interpolation geospatial interpolator knn sphere algorithm
Platform: UNKNOWN
Classifier: Development Status :: 5 - Production/Stable
Classifier: Intended Audience :: Developers
Classifier: Intended Audience :: Science/Research
Classifier: Topic :: Scientific/Engineering
Classifier: Topic :: Scientific/Engineering :: GIS
Classifier: License :: OSI Approved :: MIT License
Classifier: Programming Language :: Python :: 2
Classifier: Programming Language :: Python :: 2.7
Classifier: Programming Language :: Python :: 3
Classifier: Programming Language :: Python :: 3.4
Classifier: Programming Language :: Python :: 3.5
Classifier: Programming Language :: Python :: 3.6
Classifier: Programming Language :: Python :: 3.7
Requires-Python: >=2.7, !=3.0.*, !=3.1.*, !=3.2.*, !=3.3.*
Requires-Dist: numpy (>=1.16.1)
Requires-Dist: scipy (>=1.2.1)
Provides-Extra: dist
Requires-Dist: twine ; extra == 'dist'
Requires-Dist: wheel ; extra == 'dist'
